deep_quality_estimation/.gitignore
deep_quality_estimation/__init__.py
deep_quality_estimation/center_of_mass.py
deep_quality_estimation/data_handler.py
deep_quality_estimation/enums.py
deep_quality_estimation/model.py
deep_quality_estimation/transforms.py
deep_quality_estimation/weights/dqe_weights.pth
deep_quality_estimation-0.0.3.dist-info/METADATA
deep_quality_estimation-0.0.3.dist-info/WHEEL
deep_quality_estimation-0.0.3.dist-info/RECORD
