Metadata-Version: 2.1
Name: deep_quality_estimation
Version: 0.0.3
Summary: 
Home-page: https://github.com/BrainLesion/deep_quality_estimation
Author: Marcel Rosier
Author-email: marcel.rosier@tum.de>, Florian Kofler <florian.kofler@tum.de
Requires-Python: >=3.9
Classifier: Programming Language :: Python :: 3
Classifier: Programming Language :: Python :: 3.9
Classifier: Programming Language :: Python :: 3.10
Classifier: Programming Language :: Python :: 3.11
Classifier: Programming Language :: Python :: 3.12
Classifier: Programming Language :: Python :: 3.13
Requires-Dist: loguru (>=0.7.2,<0.8.0)
Requires-Dist: monai (>=1.4.0,<2.0.0)
Requires-Dist: nibabel (>=5.3.2,<6.0.0)
Requires-Dist: numpy (>=1.21.2)
Requires-Dist: scipy (<1.14) ; python_version < "3.10"
Requires-Dist: scipy (>=1.14.1,<2.0.0) ; python_version >= "3.10"
Requires-Dist: torch (>=2.5.1,<3.0.0)
Project-URL: Documentation, https://www.TODO.com
Project-URL: Repository, https://github.com/BrainLesion/deep_quality_estimation
